Metadata-Version: 2.1
Name: reftool
Version: 2.2.0
Summary: reftool - A commandline interface for accessing reference archives
Home-page: https://github.com/usdAG/reftool
Author: Tobias Neitzel (@qtc_de)
Classifier: Programming Language :: Python :: 3
Classifier: Operating System :: Unix
Classifier: License :: OSI Approved :: GNU General Public License v3 (GPLv3)
License-File: LICENSE
